{
  "_meta": {
    "sources": [
      "loopback/common/models",
      "loopback/server/models",
      "../common/models",
      "./models"
    ],
    "mixins": [
      "loopback/common/mixins",
      "loopback/server/mixins",
      "../common/mixins",
      "./mixins"
    ]
  },
  "User": {
    "dataSource": "mongo",
    "public": false
  },
  "AccessToken": {
    "dataSource": "mongo",
    "public": false
  },
  "ACL": {
    "dataSource": "mongo",
    "public": false
  },
  "RoleMapping": {
    "dataSource": "mongo",
    "public": false
  },
  "Role": {
    "dataSource": "mongo",
    "public": false
  },
  "weatherreport": {
    "dataSource": "mongo",
    "public": true
  },
  "position": {
    "dataSource": "mongo",
    "public": true
  },
  "mobile_user": {
    "dataSource": "mongo",
    "public": true
  },
  "group": {
    "dataSource": "mongo",
    "public": true
  },
  "storage": {
    "dataSource": "storage",
    "public": true
  },
  "Checkpoint": {
    "dataSource": "mongo",
    "public": false
  },
  "Change": {
    "dataSource": "mongo",
    "public": false
  }
}
